futu_stock_mcp_server/__init__.py
futu_stock_mcp_server/server.py
mseep_futu_stock_mcp_server-0.1.1.dist-info/METADATA
mseep_futu_stock_mcp_server-0.1.1.dist-info/WHEEL
mseep_futu_stock_mcp_server-0.1.1.dist-info/RECORD
